sap_bdc_mcp/__init__.py
sap_bdc_mcp/config.py
sap_bdc_mcp/local_client.py
sap_bdc_mcp/server.py
sap_bdc_mcp_server-0.2.0.dist-info/licenses/LICENSE
sap_bdc_mcp_server-0.2.0.dist-info/METADATA
sap_bdc_mcp_server-0.2.0.dist-info/WHEEL
sap_bdc_mcp_server-0.2.0.dist-info/entry_points.txt
sap_bdc_mcp_server-0.2.0.dist-info/top_level.txt
sap_bdc_mcp_server-0.2.0.dist-info/RECORD
