Metadata-Version: 2.4
Name: sap-bdc-mcp-server
Version: 0.2.0
Summary: MCP server for SAP Business Data Cloud integration with 7 tools including validation and provisioning
Author-email: Mario DeFelipe <mario.defelipe@example.com>
License-Expression: MIT
Requires-Python: >=3.9
License-File: LICENSE
Requires-Dist: mcp>=1.0.0
Requires-Dist: sap-bdc-connect-sdk>=1.1.6
Provides-Extra: dev
Requires-Dist: pytest>=7.0.0; extra == "dev"
Requires-Dist: pytest-asyncio>=0.21.0; extra == "dev"
Dynamic: license-file
